offbyone/__init__.py
offbyone-0.1.dist-info/DESCRIPTION.rst
offbyone-0.1.dist-info/METADATA
offbyone-0.1.dist-info/RECORD
offbyone-0.1.dist-info/WHEEL
offbyone-0.1.dist-info/metadata.json
offbyone-0.1.dist-info/top_level.txt
